{"schema_version": 2, "dt": 0.06666666666666667, "task": "BananaInBowlTask", "env_id": 0, "run": 0, "success": true, "final_step": 177, "events": [{"step": 108, "code": 139, "name": "OBJECT_GRABBED_SUCCESS", "info": "success: object_grabbed(object=banana). advanced 1 step(s) to step 1 for banana.", "score": 0.0}, {"step": 175, "code": 263, "name": "TARGET_OBJECT_DROPPED", "info": "Target object dropped during transport", "score": 0.0}, {"step": 175, "code": 248, "name": "OBJECT_GRABBED_FAILURE", "info": "failed: object_grabbed(object=banana). regressing to step 0 for banana.", "score": 0.0}, {"step": 176, "code": 139, "name": "OBJECT_GRABBED_SUCCESS", "info": "Completed subtask 'pick_and_place' 1/1", "score": 1.0}]}